unitorch/__init__.py
unitorch/cli/__init__.py
unitorch/cli/core.py
unitorch/cli/decorators.py
unitorch/cli/wandb.py
unitorch/cli/assets/icon.png
unitorch/cli/assets/style.css
unitorch/cli/consoles/__init__.py
unitorch/cli/consoles/eval.py
unitorch/cli/consoles/fastapi.py
unitorch/cli/consoles/infer.py
unitorch/cli/consoles/launch.py
unitorch/cli/consoles/service.py
unitorch/cli/consoles/train.py
unitorch/cli/consoles/webui.py
unitorch/cli/datasets/__init__.py
unitorch/cli/datasets/hf.py
unitorch/cli/datasets/megatron.py
unitorch/cli/fastapis/__init__.py
unitorch/cli/fastapis/bria.py
unitorch/cli/fastapis/info.py
unitorch/cli/fastapis/llava.py
unitorch/cli/fastapis/qwen.py
unitorch/cli/fastapis/qwen_vl.py
unitorch/cli/fastapis/controlnet/__init__.py
unitorch/cli/fastapis/controlnet/image2image.py
unitorch/cli/fastapis/controlnet/inpainting.py
unitorch/cli/fastapis/controlnet/text2image.py
unitorch/cli/fastapis/controlnet_3/__init__.py
unitorch/cli/fastapis/controlnet_3/text2image.py
unitorch/cli/fastapis/controlnet_flux/__init__.py
unitorch/cli/fastapis/controlnet_flux/image2image.py
unitorch/cli/fastapis/controlnet_flux/inpainting.py
unitorch/cli/fastapis/controlnet_flux/text2image.py
unitorch/cli/fastapis/controlnet_xl/__init__.py
unitorch/cli/fastapis/controlnet_xl/image2image.py
unitorch/cli/fastapis/controlnet_xl/inpainting.py
unitorch/cli/fastapis/controlnet_xl/text2image.py
unitorch/cli/fastapis/qwen_image/__init__.py
unitorch/cli/fastapis/qwen_image/image_editing.py
unitorch/cli/fastapis/qwen_image/text2image.py
unitorch/cli/fastapis/stable/__init__.py
unitorch/cli/fastapis/stable/image2image.py
unitorch/cli/fastapis/stable/image2video.py
unitorch/cli/fastapis/stable/inpainting.py
unitorch/cli/fastapis/stable/interrogator.py
unitorch/cli/fastapis/stable/resolution.py
unitorch/cli/fastapis/stable/text2image.py
unitorch/cli/fastapis/stable_3/__init__.py
unitorch/cli/fastapis/stable_3/image2image.py
unitorch/cli/fastapis/stable_3/inpainting.py
unitorch-0.0.1.4.dist-info/LICENSE
unitorch-0.0.1.4.dist-info/METADATA
unitorch-0.0.1.4.dist-info/WHEEL
unitorch-0.0.1.4.dist-info/entry_points.txt
unitorch-0.0.1.4.dist-info/top_level.txt
unitorch-0.0.1.4.dist-info/RECORD
