Metadata-Version: 2.1
Name: unitorch
Version: 0.0.1.4
Summary: unitorch provides efficient implementation of popular unified NLU / NLG / CV / CTR / MM / RL models with PyTorch.
Author-email: fuliucansheng <fuliucansheng@gmail.com>
License: MIT
Keywords: PyTorch
Classifier: Development Status :: 5 - Production/Stable
Classifier: Intended Audience :: Developers
Classifier: Intended Audience :: Education
Classifier: Intended Audience :: Science/Research
Classifier: License :: OSI Approved :: MIT License
Classifier: Operating System :: OS Independent
Classifier: Programming Language :: Python :: 3.10
Classifier: Programming Language :: Python :: 3.11
Classifier: Programming Language :: Python :: 3.12
Classifier: Topic :: Scientific/Engineering :: Artificial Intelligence
Requires-Python: >=3.10
License-File: LICENSE
Requires-Dist: configparser
Requires-Dist: pillow
Requires-Dist: imageio[ffmpeg]
Requires-Dist: matplotlib
Requires-Dist: sentencepiece
Requires-Dist: importlib-resources
Requires-Dist: fire>=0.2.1
Requires-Dist: numpy<2.0.0
Requires-Dist: pandas<=1.5.3
Requires-Dist: scikit-learn>=0.24.2
Requires-Dist: transformers>=4.52.4
Requires-Dist: datasets>=2.12.0
Requires-Dist: peft>=0.7.0
Requires-Dist: safetensors>=0.3.1
Provides-Extra: all
Requires-Dist: unitorch[deepspeed,diffusers,megatron,others,quantization]; extra == "all"
Provides-Extra: deepspeed
Requires-Dist: deepspeed>=0.11.0; extra == "deepspeed"
Provides-Extra: detection
Requires-Dist: timm>=1.0.0; extra == "detection"
Provides-Extra: diffusers
Requires-Dist: diffusers>=0.35.1; extra == "diffusers"
Requires-Dist: torchsde>=0.2.6; extra == "diffusers"
Provides-Extra: docs
Requires-Dist: mkdocstrings[python]>=0.18; extra == "docs"
Requires-Dist: mkdocs-material; extra == "docs"
Requires-Dist: markdown-exec; extra == "docs"
Requires-Dist: mkdocs-gen-files; extra == "docs"
Requires-Dist: mkdocs-coverage; extra == "docs"
Provides-Extra: megatron
Requires-Dist: megatron-core>=0.12.0; extra == "megatron"
Provides-Extra: others
Requires-Dist: gradio>=5.0.0; extra == "others"
Requires-Dist: fastapi>=0.103.1; extra == "others"
Requires-Dist: wandb; extra == "others"
Requires-Dist: uvicorn; extra == "others"
Requires-Dist: python-multipart; extra == "others"
Requires-Dist: onnxruntime; extra == "others"
Provides-Extra: quantization
Requires-Dist: bitsandbytes>=0.41.1; extra == "quantization"
